efcamdat/__init__.py
efcamdat/cli.py
efcamdat/transform.py
efcamdat-0.0.5.dist-info/LICENSE
efcamdat-0.0.5.dist-info/METADATA
efcamdat-0.0.5.dist-info/WHEEL
efcamdat-0.0.5.dist-info/entry_points.txt
efcamdat-0.0.5.dist-info/RECORD
